commlab/__init__.py
commlab/main.py
commlab-0.3.0.dist-info/METADATA
commlab-0.3.0.dist-info/WHEEL
commlab-0.3.0.dist-info/top_level.txt
commlab-0.3.0.dist-info/RECORD
